PiGPS-0.1.1.dist-info/DESCRIPTION.rst
PiGPS-0.1.1.dist-info/METADATA
PiGPS-0.1.1.dist-info/RECORD
PiGPS-0.1.1.dist-info/WHEEL
PiGPS-0.1.1.dist-info/metadata.json
PiGPS-0.1.1.dist-info/top_level.txt
pigps/__init__.py
pigps/piGPS.py
