Metadata-Version: 2.0
Name: PiGPS
Version: 0.1.1
Summary: GPS library for consuming location data from serial interface
Home-page: https://github.com/raspberrypilearning/piGPS
Author: James Robinson
Author-email: james.robinson@raspberrypi.org
License: BSD
Keywords: gps mapping
Platform: UNKNOWN
Classifier: Development Status :: 3 - Alpha
Classifier: Programming Language :: Python :: 3
Classifier: Programming Language :: Python :: 2
Classifier: Topic :: Education
Classifier: Topic :: Scientific/Engineering :: GIS
Classifier: Intended Audience :: Education
Classifier: Intended Audience :: Developers
Classifier: License :: OSI Approved :: BSD License
Requires-Dist: pyserial
